navigation/BasicMask.py
navigation/GoogleAPI.py
navigation/MaskSet.py
navigation/Navigator.py
navigation/Skill.py
navigation/__init__.py
navigation/find_common.py
navigation-0.1.dist-info/METADATA
navigation-0.1.dist-info/WHEEL
navigation-0.1.dist-info/top_level.txt
navigation-0.1.dist-info/RECORD
